lambdatest_playwright_driver/__init__.py
lambdatest_playwright_driver/smartui.py
lambdatest_playwright_driver/version.py
lambdatest_playwright_driver-1.0.0.dist-info/METADATA
lambdatest_playwright_driver-1.0.0.dist-info/WHEEL
lambdatest_playwright_driver-1.0.0.dist-info/top_level.txt
lambdatest_playwright_driver-1.0.0.dist-info/RECORD
