Metadata-Version: 2.1
Name: lambdatest-playwright-driver
Version: 1.0.0
Summary: Python Playwright SDK for visual testing with Smart UI
Home-page: https://github.com/LambdaTest/lambdatest-python-sdk
Author: LambdaTest <keys@lambdatest.com>
License: MIT
Keywords: lambdatest python playwright sdk visual testing
Classifier: Development Status :: 5 - Production/Stable
Classifier: Programming Language :: Python :: 3
Classifier: Natural Language :: English
Classifier: License :: OSI Approved :: MIT License
Classifier: Topic :: Software Development :: Testing
Requires-Python: >=3.7
Requires-Dist: playwright >=1.12
Requires-Dist: lambdatest-sdk-utils
